seven_segment.v
module seven_segment (
    input wire [3:0] digit,
    output reg [6:0] seg
);

always @(*) begin
    case(digit) 
        4'b0000:seg = 7'b1111110;
        4'b0001:seg=7'b0110000;
        4'b0010:seg=7'b1101101;
        4'b0011:seg=7'b1111001;
        4'b0100:seg=7'b1110011;
        4'b0101:seg=7'b1011011;
        4'b0110:seg=7'b1011111;
        4'b0111:seg=7'b1110000;
        4'b1000:seg=7'b1111111;
        4'b1001:seg=7'b1111011;
        default: seg = 7'b0000000;
    endcase
end
endmodule

seven_segment_tb.v
`timescale 1ns/1ps
`include "seven_segment.v"

module seven_segment_tb;

reg [3:0] digit;
wire [6:0] seg;

seven_segment dut (
    .digit(digit),.seg(seg)
);

integer i;
initial begin
    $dumpfile("seven_segment.vcd");  // name of dump file
    $dumpvars(0, seven_segment_tb); // dump everything in tb
     $display("Starting 7-segment testbench...");

        // Loop through 0–15
        for (i = 0; i < 16; i = i + 1) begin
            digit = i;
            #10; 
            $display("Input = %h -> Segments = %b", digit, seg);
        end

        $display("Simulation complete.");
        $stop; 
end

endmodule

seven_segment.vcd
$date
	Thu Aug 21 14:55:41 2025
$end
$version
	Icarus Verilog
$end
$timescale
	1ps
$end
$scope module seven_segment_tb $end
$var wire 7 ! seg [6:0] $end
$var reg 4 " digit [3:0] $end
$var integer 32 # i [31:0] $end
$scope module dut $end
$var wire 4 $ digit [3:0] $end
$var reg 7 % seg [6:0] $end
$upscope $end
$upscope $end
$enddefinitions $end
$comment Show the parameter values. $end
$dumpall
$end
#0
$dumpvars
b1111110 %
b0 $
b0 #
b0 "
b1111110 !
$end
#10000
b110000 !
b110000 %
b1 "
b1 $
b1 #
#20000
b1101101 !
b1101101 %
b10 "
b10 $
b10 #
#30000
b1111001 !
b1111001 %
b11 "
b11 $
b11 #
#40000
b1110011 !
b1110011 %
b100 "
b100 $
b100 #
#50000
b1011011 !
b1011011 %
b101 "
b101 $
b101 #
#60000
b1011111 !
b1011111 %
b110 "
b110 $
b110 #
#70000
b1110000 !
b1110000 %
b111 "
b111 $
b111 #
#80000
b1111111 !
b1111111 %
b1000 "
b1000 $
b1000 #
#90000
b1111011 !
b1111011 %
b1001 "
b1001 $
b1001 #
#100000
b0 !
b0 %
b1010 "
b1010 $
b1010 #
#110000
b1011 "
b1011 $
b1011 #
#120000
b1100 "
b1100 $
b1100 #
#130000
b1101 "
b1101 $
b1101 #
#140000
b1110 "
b1110 $
b1110 #
#150000
b1111 "
b1111 $
b1111 #
#160000
b10000 #
